[{"start": 103, "end": 110, "name": "\u9632\u75ab\u79d1\u6280", "id": "main_0", "displayOrder": 1}, {"start": 103, "end": 110, "name": "\u8cc7\u5b89\u4eba\u57f9\u8207\u6578\u4f4d\u7d93\u6fdf", "id": "main_1", "displayOrder": 108}, {"start": 103, "end": 110, "name": "\u80fd\u6e90", "id": "main_2", "displayOrder": 327}, {"start": 103, "end": 110, "name": "\u7cbe\u6e96\u91ab\u7642\u8207\u7cbe\u6e96\u5065\u5eb7", "id": "main_3", "displayOrder": 716}, {"start": 103, "end": 110, "name": "\u667a\u6167\u8fb2\u696d", "id": "main_4", "displayOrder": 960}, {"start": 103, "end": 110, "name": "\u5275\u65b0\u5275\u696d", "id": "main_5", "displayOrder": 1120}, {"start": 103, "end": 110, "name": "5G", "id": "main_6", "displayOrder": 1280}, {"start": 103, "end": 110, "name": "8", "id": "main_7", "displayOrder": 1507}, {"start": 103, "end": 110, "name": "5", "id": "main_8", "displayOrder": 1658}, {"start": 103, "end": 110, "name": "4", "id": "main_9", "displayOrder": 1763}, {"start": 103, "end": 110, "name": "3", "id": "main_10", "displayOrder": 1900}, {"start": 103, "end": 110, "name": "2", "id": "main_11", "displayOrder": 2107}, {"start": 103, "end": 110, "name": "19", "id": "main_12", "displayOrder": 2307}, {"start": 103, "end": 110, "name": "18", "id": "main_13", "displayOrder": 2439}, {"start": 103, "end": 110, "name": "17", "id": "main_14", "displayOrder": 2576}, {"start": 103, "end": 110, "name": "16", "id": "main_15", "displayOrder": 2616}, {"start": 103, "end": 110, "name": "15", "id": "main_16", "displayOrder": 2668}, {"start": 103, "end": 110, "name": "13", "id": "main_17", "displayOrder": 2769}, {"start": 103, "end": 110, "name": "11", "id": "main_18", "displayOrder": 2920}, {"start": 103, "end": 110, "name": "10", "id": "main_19", "displayOrder": 3017}]